sqlitemanager/__init__.py
sqlitemanager/handler.py
sqlitemanager/objects.py
sqlitemanager-0.7.2.dist-info/LICENSE
sqlitemanager-0.7.2.dist-info/METADATA
sqlitemanager-0.7.2.dist-info/WHEEL
sqlitemanager-0.7.2.dist-info/top_level.txt
sqlitemanager-0.7.2.dist-info/RECORD
