Metadata-Version: 2.1
Name: sqlitemanager
Version: 0.7.2
Summary: Handler object for easy sqlite manipulation
Home-page: https://github.com/Michael-Yongshi/SQLiteManager
Author: Michael-Yongshi
Author-email: 4registration@outlook.com
Classifier: Programming Language :: Python :: 3
Classifier: License :: OSI Approved :: GNU General Public License v3 or later (GPLv3+)
Classifier: Operating System :: OS Independent
Requires-Python: >=3.7
License-File: LICENSE
